orthpol_light.cpython-310-x86_64-linux-gnu.so
orthpol_light-2.0.2.dist-info/RECORD
orthpol_light-2.0.2.dist-info/METADATA
orthpol_light-2.0.2.dist-info/WHEEL
