Metadata-Version: 2.1
Name: orthpol-light
Version: 2.0.2
Summary: Light python wrapper for the ORTHPOL package
Author-Email: Daniele Bigoni <dabi@limitcycle.it>
License: LGPL
Requires-Python: >=3.8
